.coafile
.gitignore
.gitlab-ci.yml
.travis.yml
LICENSE
README.md
requirements.setup.txt
requirements.test.txt
setup.py
alpakka/__init__.py
alpakka/__main__.py
alpakka/commands.py
alpakka/logger.py
alpakka.egg-info/PKG-INFO
alpakka.egg-info/SOURCES.txt
alpakka.egg-info/dependency_links.txt
alpakka.egg-info/entry_points.txt
alpakka.egg-info/requires.txt
alpakka.egg-info/top_level.txt
alpakka/pyang_plugins/__init__.py
alpakka/pyang_plugins/alpakkaplugin.py
alpakka/wools/__init__.py
alpakka/wools/default_wool.py
alpakka/wrapper/__init__.py
alpakka/wrapper/grouponder.py
alpakka/wrapper/nodewrapper.py
alpakka/wrapper/typonder.py
test/conftest.py
test/test_wrapper.py
test/virtual-topology-api.yang
test/json_test_wool/json_test_wool/json_test_wool - Verknüpfung.lnk