Metadata-Version: 1.2
Name: alpakka
Version: 0.1.dev153
Summary: Cutest YANG Eater alive
Home-page: UNKNOWN
Author: ADVA Optical Networking
Maintainer: Thomas Szyrkowiec
Maintainer-email: tszyrkowiec@advaoptical.com
License: Apache License 2.0
Keywords: alpakka,yang,pyang,wool,wools
Platform: UNKNOWN
Classifier: Development Status :: 3 - Alpha
Classifier: Intended Audience :: Developers
Classifier: Intended Audience :: Information Technology
Classifier: Intended Audience :: Telecommunications Industry
Classifier: License :: OSI Approved :: Apache Software License
Classifier: Operating System :: OS Independent
Classifier: Programming Language :: Python
Classifier: Programming Language :: Python :: 3
Classifier: Programming Language :: Python :: 3.5
Classifier: Programming Language :: Python :: 3.6
Classifier: Programming Language :: Python :: 3.7
Classifier: Topic :: Software Development
Classifier: Topic :: Software Development :: Code Generators
Classifier: Topic :: Utilities
